dcactivity/__init__.py
dcactivity/dcactivity.py
dcactivity/errors.py
dcactivity-1.2.dist-info/LICENSE
dcactivity-1.2.dist-info/METADATA
dcactivity-1.2.dist-info/WHEEL
dcactivity-1.2.dist-info/top_level.txt
dcactivity-1.2.dist-info/RECORD
