Metadata-Version: 2.1
Name: dcactivity
Version: 1.2
Summary: A python module to access and utilize Beta Discord VC Party features like YouTube, Poker Night, etc. with your Bot
Home-page: https://github.com/AkshuAgarwal/DCActivity
Author: AkshuAgarwal
Author-email: akshitagarwal2204@gmail.com
License: MIT
Project-URL: Issue Tracker, https://github.com/AkshuAgarwal/DCActivity/issues
Project-URL: Source Code, https://github.com/AkshuAgarwal/DCActivity
Platform: UNKNOWN
Classifier: Development Status :: 5 - Production/Stable
Classifier: Intended Audience :: Developers
Classifier: License :: OSI Approved :: MIT License
Classifier: Natural Language :: English
Classifier: Operating System :: OS Independent
Classifier: Programming Language :: Python :: 3.6
Classifier: Programming Language :: Python :: 3.7
Classifier: Programming Language :: Python :: 3.8
Classifier: Programming Language :: Python :: 3.9
Classifier: Topic :: Software Development :: Libraries :: Python Modules
Requires-Python: >=3.6
License-File: LICENSE
Requires-Dist: discord.py (>=1.5.0)
